lscae/__init__.py
lscae-0.0.2.dist-info/LICENSE
lscae-0.0.2.dist-info/METADATA
lscae-0.0.2.dist-info/WHEEL
lscae-0.0.2.dist-info/top_level.txt
lscae-0.0.2.dist-info/RECORD
