Metadata-Version: 2.1
Name: lscae
Version: 0.0.2
Summary: Laplacian Score-regularized CAE
Home-page: https://github.com/jsvir/lscae
Author: Jonathan Svirsky
Author-email: js@alumni.technion.ac.il
Classifier: Programming Language :: Python :: 3
Classifier: License :: OSI Approved :: MIT License
Classifier: Operating System :: OS Independent
Requires-Python: >=3.7
License-File: LICENSE
Requires-Dist: torch
Requires-Dist: scikit-learn
Requires-Dist: omegaconf
Requires-Dist: scipy
Requires-Dist: matplotlib
